{
  "name": "VwTeamUsers",
  "base": "PersistedModel",
  "idInjection": false,
  "options": {
    "validateUpsert": true
  },
  "mysql": {
    "schema": "memex_sotera",
    "table": "vw_team_users"
  },
  "properties": {
    "name": {
      "type": "String",
      "required": false,
      "length": 100,
      "precision": null,
      "scale": null,
      "mysql": {
        "columnName": "name",
        "dataType": "varchar",
        "dataLength": 100,
        "dataPrecision": null,
        "dataScale": null,
        "nullable": "Y"
      },
      "_selectable": true
    },
    "id": {
      "type": "Number",
      "id": true,
      "required": true,
      "length": null,
      "precision": 10,
      "scale": 0,
      "mysql": {
        "columnName": "id",
        "dataType": "int",
        "dataLength": null,
        "dataPrecision": 10,
        "dataScale": 0,
        "nullable": "N"
      },
      "_selectable": false
    }
  },
  "validations": [],
  "relations": {},
  "acls": [],
  "methods": []
}
